svg2png_clipboard/__init__.py
svg2png_clipboard/cli.py
svg2png_clipboard/core.py
svg2png_clipboard-0.1.0.dist-info/licenses/LICENSE
svg2png_clipboard-0.1.0.dist-info/METADATA
svg2png_clipboard-0.1.0.dist-info/WHEEL
svg2png_clipboard-0.1.0.dist-info/entry_points.txt
svg2png_clipboard-0.1.0.dist-info/top_level.txt
svg2png_clipboard-0.1.0.dist-info/RECORD
