Metadata-Version: 2.4
Name: svg2png-clipboard
Version: 0.1.0
Summary: Convert SVG from clipboard to PNG and copy back to clipboard
Author-email: Hsieh-Ting Lin <hsieh.ting.lin@gmail.com>
License: MIT
Project-URL: Homepage, https://github.com/yourusername/svg2png-clipboard
Project-URL: Issues, https://github.com/yourusername/svg2png-clipboard/issues
Classifier: Development Status :: 4 - Beta
Classifier: Environment :: Console
Classifier: Intended Audience :: Developers
Classifier: License :: OSI Approved :: MIT License
Classifier: Operating System :: MacOS
Classifier: Programming Language :: Python :: 3
Classifier: Programming Language :: Python :: 3.8
Classifier: Programming Language :: Python :: 3.9
Classifier: Programming Language :: Python :: 3.10
Classifier: Programming Language :: Python :: 3.11
Classifier: Programming Language :: Python :: 3.12
Classifier: Topic :: Utilities
Requires-Python: >=3.8
License-File: LICENSE
Requires-Dist: pyperclipimg
Requires-Dist: click>=8.0
Dynamic: license-file
